{
  "id": null,
  "title": "Kubernetes Dashboard",
  "tags": ["homelab", "kubernetes"],
  "style": "dark",
  "timezone": "browser",
  "refresh": "30s",
  "time": {
    "from": "now-1h",
    "to": "now"
  },
  "panels": [
    {
      "id": 1,
      "title": "Cluster Status",
      "type": "stat",
      "targets": [
        {
          "expr": "kube_node_info",
          "legendFormat": "{{node}}"
        }
      ],
      "fieldConfig": {
        "defaults": {
          "color": {"mode": "thresholds"},
          "thresholds": {
            "steps": [
              {"color": "red", "value": null},
              {"color": "green", "value": 1}
            ]
          },
          "mappings": [
            {"options": {"1": {"text": "Ready"}}, "type": "value"}
          ]
        }
      },
      "gridPos": {"h": 4, "w": 6, "x": 0, "y": 0}
    },
    {
      "id": 2,
      "title": "ArgoCD Status",
      "type": "stat",
      "targets": [
        {
          "expr": "argocd_app_health_status{health_status=\"Healthy\"}",
          "legendFormat": "Healthy Apps"
        }
      ],
      "fieldConfig": {
        "defaults": {
          "color": {"mode": "thresholds"},
          "thresholds": {
            "steps": [
              {"color": "red", "value": null},
              {"color": "green", "value": 1}
            ]
          }
        }
      },
      "gridPos": {"h": 4, "w": 6, "x": 6, "y": 0}
    },
    {
      "id": 3,
      "title": "Running Pods",
      "type": "stat",
      "targets": [
        {
          "expr": "count(kube_pod_status_phase{phase=\"Running\"})",
          "legendFormat": "Running"
        }
      ],
      "fieldConfig": {
        "defaults": {
          "color": {"mode": "palette-classic"}
        }
      },
      "gridPos": {"h": 4, "w": 6, "x": 12, "y": 0}
    },
    {
      "id": 4,
      "title": "Failed Pods",
      "type": "stat",
      "targets": [
        {
          "expr": "count(kube_pod_status_phase{phase=\"Failed\"})",
          "legendFormat": "Failed"
        }
      ],
      "fieldConfig": {
        "defaults": {
          "color": {"mode": "thresholds"},
          "thresholds": {
            "steps": [
              {"color": "green", "value": null},
              {"color": "red", "value": 1}
            ]
          }
        }
      },
      "gridPos": {"h": 4, "w": 6, "x": 18, "y": 0}
    },
    {
      "id": 5,
      "title": "Pod Status by Namespace",
      "type": "table",
      "targets": [
        {
          "expr": "kube_pod_status_phase",
          "legendFormat": "{{namespace}}/{{pod}}",
          "format": "table",
          "instant": true
        }
      ],
      "transformations": [
        {
          "id": "organize",
          "options": {
            "excludeByName": {
              "Time": true,
              "__name__": true,
              "instance": true,
              "job": true,
              "uid": true
            },
            "renameByName": {
              "namespace": "Namespace",
              "pod": "Pod",
              "phase": "Status"
            }
          }
        }
      ],
      "gridPos": {"h": 8, "w": 12, "x": 0, "y": 4}
    },
    {
      "id": 6,
      "title": "Resource Usage by Namespace",
      "type": "timeseries",
      "targets": [
        {
          "expr": "sum(rate(container_cpu_usage_seconds_total[5m])) by (namespace) * 100",
          "legendFormat": "{{namespace}} CPU"
        }
      ],
      "fieldConfig": {
        "defaults": {
          "unit": "percent"
        }
      },
      "gridPos": {"h": 8, "w": 12, "x": 12, "y": 4}
    },
    {
      "id": 7,
      "title": "Memory Usage by Namespace",
      "type": "timeseries",
      "targets": [
        {
          "expr": "sum(container_memory_usage_bytes) by (namespace) / 1024 / 1024",
          "legendFormat": "{{namespace}}"
        }
      ],
      "fieldConfig": {
        "defaults": {
          "unit": "MiB"
        }
      },
      "gridPos": {"h": 8, "w": 12, "x": 0, "y": 12}
    },
    {
      "id": 8,
      "title": "Longhorn Volume Status",
      "type": "table",
      "targets": [
        {
          "expr": "longhorn_volume_actual_size_bytes",
          "legendFormat": "{{volume}}",
          "format": "table",
          "instant": true
        }
      ],
      "fieldConfig": {
        "defaults": {
          "unit": "binBps",
          "color": {"mode": "thresholds"},
          "thresholds": {
            "steps": [
              {"color": "green", "value": null},
              {"color": "yellow", "value": 1000000000},
              {"color": "red", "value": 10000000000}
            ]
          }
        }
      },
      "transformations": [
        {
          "id": "organize",
          "options": {
            "excludeByName": {
              "Time": true,
              "__name__": true,
              "instance": true,
              "job": true
            },
            "renameByName": {
              "volume": "Volume",
              "Value": "Size"
            }
          }
        }
      ],
      "gridPos": {"h": 8, "w": 12, "x": 12, "y": 12}
    }
  ]
}